{
  "year": "2025",
  "month": "11",
  "days": {
    "21": "data/2025/11/21-11.json",
    "20": "data/2025/11/20-11.json",
    "19": "data/2025/11/19-11.json",
    "18": "data/2025/11/18-11.json",
    "17": "data/2025/11/17-11.json",
    "16": "data/2025/11/16-11.json",
    "15": "data/2025/11/15-11.json",
    "14": "data/2025/11/14-11.json",
    "13": "data/2025/11/13-11.json",
    "12": "data/2025/11/12-11.json",
    "11": "data/2025/11/11-11.json",
    "10": "data/2025/11/10-11.json",
    "09": "data/2025/11/09-11.json"
  }
}